{
 "actions": [],
 "allow_rename": 1,
 "creation": "2024-05-07 14:20:31.274069",
 "doctype": "DocType",
 "editable_grid": 1,
 "engine": "InnoDB",
 "field_order": [
  "allergens"
 ],
 "fields": [
  {
   "fieldname": "allergens",
   "fieldtype": "Link",
   "in_list_view": 1,
   "label": "Allergens",
   "options": "Allergens",
   "reqd": 1
  }
 ],
 "index_web_pages_for_search": 1,
 "istable": 1,
 "links": [],
 "modified": "2024-05-07 15:17:45.388933",
 "modified_by": "Administrator",
 "module": "getpos",
 "name": "Item Allergens",
 "owner": "Administrator",
 "permissions": [],
 "sort_field": "modified",
 "sort_order": "DESC",
 "states": []
}